blueshed/gust/__init__.py
blueshed/gust/app.py
blueshed/gust/configs.py
blueshed/gust/context.py
blueshed/gust/json_utils.py
blueshed/gust/main.py
blueshed/gust/routes.py
blueshed/gust/static_file_handler.py
blueshed/gust/stream.py
blueshed/gust/utils.py
blueshed/gust/web.py
blueshed/gust/web_handler.py
blueshed/gust/websocket.py
blueshed_gust-0.0.25.dist-info/METADATA
blueshed_gust-0.0.25.dist-info/WHEEL
blueshed_gust-0.0.25.dist-info/top_level.txt
blueshed_gust-0.0.25.dist-info/RECORD
