Metadata-Version: 2.2
Name: blueshed-gust
Version: 0.0.25
Summary: lite additions to tornado.
Author-email: Peter Bunyan <pete@blueshed.co.uk>
License: BSD-3-Clause
Project-URL: Homepage, https://github.com/blueshed/blueshed-gust
Project-URL: Documentation, https://blueshed.github.io/blueshed-gust/blueshed/gust.html
Classifier: Programming Language :: Python :: 3
Requires-Python: >=3.12
Requires-Dist: python-dotenv
Requires-Dist: tornado
